MANIFEST.in
README.txt
setup.cfg
setup.py
docs/HISTORY.txt
docs/INSTALL.txt
docs/LICENSE.GPL
docs/LICENSE.txt
ityou/__init__.py
ityou.jsonapi.egg-info/PKG-INFO
ityou.jsonapi.egg-info/SOURCES.txt
ityou.jsonapi.egg-info/dependency_links.txt
ityou.jsonapi.egg-info/entry_points.txt
ityou.jsonapi.egg-info/namespace_packages.txt
ityou.jsonapi.egg-info/not-zip-safe
ityou.jsonapi.egg-info/paster_plugins.txt
ityou.jsonapi.egg-info/requires.txt
ityou.jsonapi.egg-info/top_level.txt
ityou/jsonapi/__init__.py
ityou/jsonapi/configure.zcml
ityou/jsonapi/interfaces.py
ityou/jsonapi/tests.py
ityou/jsonapi/json/__init__.py
ityou/jsonapi/json/configure.zcml
ityou/jsonapi/json/contentapi.py
ityou/jsonapi/json/esiparamsapi.py
ityou/jsonapi/json/json_utils.py
ityou/jsonapi/json/navigationapi.py
ityou/jsonapi/json/plone_content_api.py
ityou/jsonapi/json/plone_groups_api.py
ityou/jsonapi/json/plone_portal_api.py
ityou/jsonapi/json/plone_users_api.py
ityou/jsonapi/json/userapi.py
ityou/jsonapi/json/userprofileapi.py
ityou/jsonapi/json/interfaces/__init__.py
ityou/jsonapi/json/interfaces/content.py
ityou/jsonapi/json/interfaces/group.py
ityou/jsonapi/json/interfaces/jsonutils.py
ityou/jsonapi/json/interfaces/portal.py
ityou/jsonapi/json/interfaces/portletapi.py
ityou/jsonapi/json/interfaces/user.py
ityou/jsonapi/profiles/default/browserlayer.xml
ityou/jsonapi/profiles/default/metadata.xml