Metadata-Version: 1.1
Name: ityou.jsonapi
Version: 1.3.1
Summary: ITYOU ESI JSON API
Home-page: http://www.ityou.de/esi/
Author: ITYOU/LM
Author-email: lm@ityou.de
License: GPL
Platform: UNKNOWN
Classifier: Framework :: Plone
Classifier: Programming Language :: Python
